tests/__init__.py
tests/tests_utils.py
django_string_helpers-0.1.3.dist-info/LICENSE
django_string_helpers-0.1.3.dist-info/METADATA
django_string_helpers-0.1.3.dist-info/WHEEL
django_string_helpers-0.1.3.dist-info/top_level.txt
django_string_helpers-0.1.3.dist-info/RECORD
