Metadata-Version: 2.1
Name: django-string-helpers
Version: 0.1.3
Summary: A collection of string helper utilities for Django applications
Home-page: https://gitlab.com/rohit2096/sample-library.git
Author: Rohit Hazare
Author-email: rohithazare20@gmail.com
Classifier: Framework :: Django
Classifier: Programming Language :: Python :: 3
Classifier: License :: OSI Approved :: MIT License
Classifier: Operating System :: OS Independent
Requires-Python: >=3.6
License-File: LICENSE
Requires-Dist: Django >=3.2
